{
  "ADS": [
    {
      "adNetwork": "unity",
      "interCounter": 1,

      "admob_application_id": "ca-app-pub-3844581176339820~4914427517",
      "nativeAdmob": "ca-app-pub-3844581176339820xxxx/1727165002xx",
      "interstitialAdmob": "ca-app-pub-3844581176339820/4544900036",
      "bannerAdmob_1": "ca-app-pub-3844581176339820/7171063379",
      "bannerAdmob_2": "ca-app-pub-3844581176339820/7171063379",

      "unityID": "4625613",
      "unityRewardedID": "Rewarded_Android",
      "unityRewardedOfficialAppLink": "https://play.google.com/store/apps/details?id=yacine.tv.link",
      "unityInterID": "Interstitial_Android",
      "unityBannerID_1": "Banner_Android",
      "unityBannerID_2": "Banner_Android",

      "interstitialFacebook": "YOUR_PLACEMENT_ID",
      "bannerFacebook": "YOUR_PLACEMENT_ID",
      "nativeFacebook": "YOUR_PLACEMENT_ID",
      "nativeBannerFacebook": "YOUR_PLACEMENT_ID"
    }
  ],
  "error": false
}
